Metadata-Version: 2.1
Name: linkedin-profile-scraper-python
Version: 1.0.0
Summary: A python library to scrape user profile data from linkedin automatically.
Home-page: https://linkedin-api.datakund.com/en/latest/
Author: DataKund
Author-email: datakund@gmail.com
License: Apache License 2.0
Keywords: linkedin python bot_studio scraper user profile data web-scraping
Platform: UNKNOWN
